MANIFEST.in
README.txt
setup.cfg
setup.py
beyondskins/__init__.py
beyondskins.ploneday.site2010.egg-info/PKG-INFO
beyondskins.ploneday.site2010.egg-info/SOURCES.txt
beyondskins.ploneday.site2010.egg-info/dependency_links.txt
beyondskins.ploneday.site2010.egg-info/entry_points.txt
beyondskins.ploneday.site2010.egg-info/namespace_packages.txt
beyondskins.ploneday.site2010.egg-info/not-zip-safe
beyondskins.ploneday.site2010.egg-info/requires.txt
beyondskins.ploneday.site2010.egg-info/top_level.txt
beyondskins/ploneday/__init__.py
beyondskins/ploneday/site2010/README.txt
beyondskins/ploneday/site2010/__init__.py
beyondskins/ploneday/site2010/configure.zcml
beyondskins/ploneday/site2010/profiles.zcml
beyondskins/ploneday/site2010/setuphandlers.py
beyondskins/ploneday/site2010/skins.zcml
beyondskins/ploneday/site2010/tests.py
beyondskins/ploneday/site2010/updateTranslations.sh
beyondskins/ploneday/site2010/version.txt
beyondskins/ploneday/site2010/browser/__init__.py
beyondskins/ploneday/site2010/browser/configure.zcml
beyondskins/ploneday/site2010/browser/interfaces.py
beyondskins/ploneday/site2010/browser/viewlets.py
beyondskins/ploneday/site2010/browser/images/README.txt
beyondskins/ploneday/site2010/browser/stylesheets/README.txt
beyondskins/ploneday/site2010/browser/templates/footer.pt
beyondskins/ploneday/site2010/browser/templates/logo.pt
beyondskins/ploneday/site2010/browser/templates/viewlet.pt
beyondskins/ploneday/site2010/doc/__init__.py
beyondskins/ploneday/site2010/doc/browser.txt
beyondskins/ploneday/site2010/doc/wpd.jpg
beyondskins/ploneday/site2010/locales/beyondskins.ploneday.site2010.manual.pot
beyondskins/ploneday/site2010/locales/beyondskins.ploneday.site2010.pot
beyondskins/ploneday/site2010/locales/empty.pt
beyondskins/ploneday/site2010/locales/pt_BR/LC_MESSAGES/beyondskins.ploneday.site2010.po
beyondskins/ploneday/site2010/profiles/default/actions.xml
beyondskins/ploneday/site2010/profiles/default/beyondskins.site2010_various.txt
beyondskins/ploneday/site2010/profiles/default/cssregistry.xml
beyondskins/ploneday/site2010/profiles/default/import_steps.xml
beyondskins/ploneday/site2010/profiles/default/jsregistry.xml
beyondskins/ploneday/site2010/profiles/default/metadata.xml
beyondskins/ploneday/site2010/profiles/default/skins.xml
beyondskins/ploneday/site2010/profiles/default/viewlets.xml
beyondskins/ploneday/site2010/skins/beyondskins_ploneday_site2010_images/CONTENT.txt
